tiramisu_brulee/__init__.py
tiramisu_brulee/loss.py
tiramisu_brulee/py.typed
tiramisu_brulee/util.py
tiramisu_brulee/experiment/__init__.py
tiramisu_brulee/experiment/data.py
tiramisu_brulee/experiment/lesion_tools.py
tiramisu_brulee/experiment/parse.py
tiramisu_brulee/experiment/seg.py
tiramisu_brulee/experiment/type.py
tiramisu_brulee/experiment/util.py
tiramisu_brulee/experiment/cli/__init__.py
tiramisu_brulee/experiment/cli/common.py
tiramisu_brulee/experiment/cli/predict.py
tiramisu_brulee/experiment/cli/to_onnx.py
tiramisu_brulee/experiment/cli/train.py
tiramisu_brulee/model/__init__.py
tiramisu_brulee/model/dense.py
tiramisu_brulee/model/tiramisu.py
tiramisu_brulee-0.2.2.dist-info/LICENSE
tiramisu_brulee-0.2.2.dist-info/METADATA
tiramisu_brulee-0.2.2.dist-info/WHEEL
tiramisu_brulee-0.2.2.dist-info/entry_points.txt
tiramisu_brulee-0.2.2.dist-info/top_level.txt
tiramisu_brulee-0.2.2.dist-info/RECORD
