Metadata-Version: 2.1
Name: tiramisu-brulee
Version: 0.2.2
Summary: A 2D and 3D PyTorch implementation of the Tiramisu CNN
Home-page: https://github.com/jcreinhold/tiramisu-brulee
Author: Jacob Reinhold
Author-email: jcreinhold@gmail.com
License: Apache Software License 2.0
Project-URL: Bug Tracker, https://github.com/jcreinhold/tiramisu-brulee/issues
Project-URL: Documentation, https://tiramisu-brulee.readthedocs.io/
Keywords: tiramisu,segmentation,neural network,convolutional,pytorch
Platform: UNKNOWN
Classifier: Development Status :: 4 - Beta
Classifier: Intended Audience :: Developers
Classifier: License :: OSI Approved :: Apache Software License
Classifier: Natural Language :: English
Classifier: Programming Language :: Python :: 3
Classifier: Programming Language :: Python :: 3 :: Only
Classifier: Programming Language :: Python :: 3.6
Classifier: Programming Language :: Python :: 3.7
Classifier: Programming Language :: Python :: 3.8
Classifier: Programming Language :: Python :: 3.9
Classifier: Programming Language :: Python :: Implementation :: CPython
Classifier: Typing :: Typed
Requires-Python: >=3.6
License-File: LICENSE
Requires-Dist: torch
Provides-Extra: lesionseg
Requires-Dist: jsonargparse (~=3.12.0) ; extra == 'lesionseg'
Requires-Dist: numpy ; extra == 'lesionseg'
Requires-Dist: pandas ; extra == 'lesionseg'
Requires-Dist: pillow (>=9.0.0) ; extra == 'lesionseg'
Requires-Dist: pytorch-lightning (~=1.5.1) ; extra == 'lesionseg'
Requires-Dist: PyYAML ; extra == 'lesionseg'
Requires-Dist: ruyaml ; extra == 'lesionseg'
Requires-Dist: scikit-image ; extra == 'lesionseg'
Requires-Dist: scipy ; extra == 'lesionseg'
Requires-Dist: SimpleITK (~=2.1.0) ; extra == 'lesionseg'
Requires-Dist: torchio ; extra == 'lesionseg'
Requires-Dist: torchmetrics ; extra == 'lesionseg'
Provides-Extra: mlflow
Requires-Dist: mlflow ; extra == 'mlflow'
Provides-Extra: onnx
Requires-Dist: onnx ; extra == 'onnx'
Requires-Dist: onnxruntime ; extra == 'onnx'
